libraryshad/An_Wb.py
libraryshad/Socket.py
libraryshad/__init__.py
libraryshad/encryption.py
libraryshad/matn.py
libraryshad/shad.py
libraryshad-1.1.3.dist-info/LICENCE
libraryshad-1.1.3.dist-info/METADATA
libraryshad-1.1.3.dist-info/WHEEL
libraryshad-1.1.3.dist-info/top_level.txt
libraryshad-1.1.3.dist-info/RECORD
